rjgtoys_projects-0.1.1-py3.8-nspkg.pth
rjgtoys/projects/__init__.py
rjgtoys/projects/_jenkins.py
rjgtoys/projects/_lint.py
rjgtoys/projects/_setup.py
rjgtoys/projects/_test.py
rjgtoys/projects/cli.py
rjgtoys/projects/templates/rjgtoys/cookiecutter.json
rjgtoys/projects/templates/rjgtoys/{{cookiecutter.project.id}}/.gitignore
rjgtoys/projects/templates/rjgtoys/{{cookiecutter.project.id}}/LICENSE
rjgtoys/projects/templates/rjgtoys/{{cookiecutter.project.id}}/README.md
rjgtoys/projects/templates/rjgtoys/{{cookiecutter.project.id}}/readthedocs.yaml
rjgtoys/projects/templates/rjgtoys/{{cookiecutter.project.id}}/setup.py
rjgtoys/projects/templates/rjgtoys/{{cookiecutter.project.id}}/doc/source/conf.py
rjgtoys/projects/templates/rjgtoys/{{cookiecutter.project.id}}/doc/source/getting.rst
rjgtoys/projects/templates/rjgtoys/{{cookiecutter.project.id}}/doc/source/index.rst
rjgtoys/projects/templates/rjgtoys/{{cookiecutter.project.id}}/doc/source/overview.rst
rjgtoys/projects/templates/rjgtoys/{{cookiecutter.project.id}}/doc/source/requires.txt
rjgtoys/projects/templates/rjgtoys/{{cookiecutter.project.id}}/doc/source/todo.rst
rjgtoys/projects/templates/rjgtoys/{{cookiecutter.project.id}}/doc/source/tutorial.rst
rjgtoys/projects/templates/rjgtoys/{{cookiecutter.project.id}}/doc/source/_static/README
rjgtoys/projects/templates/rjgtoys/{{cookiecutter.project.id}}/examples/README
rjgtoys/projects/templates/rjgtoys/{{cookiecutter.project.id}}/tests/unit/test_import.py
rjgtoys/projects/templates/rjgtoys/{{cookiecutter.project.id}}/{{project.family}}/__init__.py
rjgtoys/projects/templates/rjgtoys/{{cookiecutter.project.id}}/{{project.family}}/{{project.id}}/__init__.py
rjgtoys/projects/templates/rjgtoys/{{cookiecutter.project.name}}/.gitignore
rjgtoys/projects/templates/rjgtoys/{{cookiecutter.project.name}}/LICENSE
rjgtoys/projects/templates/rjgtoys/{{cookiecutter.project.name}}/README.md
rjgtoys/projects/templates/rjgtoys/{{cookiecutter.project.name}}/setup.py
rjgtoys_projects-0.1.1.dist-info/LICENSE
rjgtoys_projects-0.1.1.dist-info/METADATA
rjgtoys_projects-0.1.1.dist-info/WHEEL
rjgtoys_projects-0.1.1.dist-info/entry_points.txt
rjgtoys_projects-0.1.1.dist-info/namespace_packages.txt
rjgtoys_projects-0.1.1.dist-info/top_level.txt
rjgtoys_projects-0.1.1.dist-info/RECORD
